fastcfg/__init__.py
fastcfg-0.1.0.dist-info/LICENSE
fastcfg-0.1.0.dist-info/METADATA
fastcfg-0.1.0.dist-info/WHEEL
fastcfg-0.1.0.dist-info/RECORD
