Metadata-Version: 2.1
Name: fastcfg
Version: 0.1.0
Summary: fastcfg is a library designed to make app configuration quick, easy, and scalable
License: MIT
Author: Breisoft
Author-email: company@breisoft.com
Requires-Python: >=3.11,<4.0
Classifier: License :: OSI Approved :: MIT License
Classifier: Programming Language :: Python :: 3
Classifier: Programming Language :: Python :: 3.11
Classifier: Programming Language :: Python :: 3.12
